convert/__init__.py
convert/__main__.py
convert/cli.py
convert/commands/__init__.py
convert/commands/audio.py
convert/commands/base.py
convert/commands/hello.py
convert/commands/video.py
convert/converter_utils/__init__.py
convert/converter_utils/utils.py
converter_cli-1.0.7.dist-info/LICENSE
converter_cli-1.0.7.dist-info/METADATA
converter_cli-1.0.7.dist-info/WHEEL
converter_cli-1.0.7.dist-info/entry_points.txt
converter_cli-1.0.7.dist-info/top_level.txt
converter_cli-1.0.7.dist-info/RECORD
