Metadata-Version: 2.1
Name: converter-cli
Version: 1.0.7
Summary: A media converter command line program in Python.
Home-page: https://github.com/patillacode/converter-cli
Author: Patilla Code
Author-email: patillacode@gmail.com
License: Apache 2.0
Keywords: cli,converter,video,audio
Platform: UNKNOWN
Classifier: Intended Audience :: Developers
Classifier: Topic :: Utilities
Classifier: License :: Public Domain
Classifier: Natural Language :: English
Classifier: Operating System :: OS Independent
Classifier: Programming Language :: Python :: 3.6
License-File: LICENSE
Requires-Dist: docopt
Requires-Dist: ffmpeg-python
Requires-Dist: termcolor
Provides-Extra: test
Requires-Dist: coverage ; extra == 'test'
Requires-Dist: pytest ; extra == 'test'
Requires-Dist: pytest-cov ; extra == 'test'
Requires-Dist: mock ; extra == 'test'
